{"id":1,"nom":"Chaussure Femme escarpain","publicites":[{"id":1,"startDate":"2017-01-18T00:00:00+0000","startTime":"2016-12-29T18:30:00+0000","pays":"cm","ville":"Yaounde","sexeAge":"femmes-majeurs","payementProcess":{"status":"created"},"status":"created"},{"id":2,"startDate":"2017-01-18T00:00:00+0000","startTime":"2016-12-29T18:30:00+0000","pays":"cm","ville":"Yaounde","sexeAge":"femmes-majeurs","status":"created"}],"description":"Chaussure a talon haut. disponible en 41, 43 couleurs jaune, bleu, rouge, maron et gris","prixDiscutable":true,"prix":3500,"origine":{"id":3,"defined":false,"grossiste":true,"moq":"1","devise":"Fcfa","details":true,"garenti":false,"dureeGarenti":"1","fournie":false},"livraison":{"id":3,"internationnal":false,"delais":7,"support":"vendeur","defined":false,"expedition":true,"domicile":false,"toutLePays":true,"enMagazin":true,"fournie":false},"payement":{"id":3,"payementLivraison":true,"moneyTransfert":true,"defined":false,"fournie":false},"retour":{"id":3,"support":"vendeur","delais":10,"fournie":false,"defined":false},"image":{"url":"5864b00e4051d.jpg","alt":"5864b00e4051d.jpg"}}